LICENSE.md
MANIFEST.in
README.rst
pyproject.toml
requirements.core.txt
setup.py
core_oaipmh_provider_app/__init__.py
core_oaipmh_provider_app/admin.py
core_oaipmh_provider_app/apps.py
core_oaipmh_provider_app/menus.py
core_oaipmh_provider_app/settings.py
core_oaipmh_provider_app/tasks.py
core_oaipmh_provider_app/urls.py
core_oaipmh_provider_app.egg-info/PKG-INFO
core_oaipmh_provider_app.egg-info/SOURCES.txt
core_oaipmh_provider_app.egg-info/dependency_links.txt
core_oaipmh_provider_app.egg-info/requires.txt
core_oaipmh_provider_app.egg-info/top_level.txt
core_oaipmh_provider_app/commons/__init__.py
core_oaipmh_provider_app/commons/constants.py
core_oaipmh_provider_app/commons/exceptions.py
core_oaipmh_provider_app/commons/status.py
core_oaipmh_provider_app/components/__init__.py
core_oaipmh_provider_app/components/oai_data/__init__.py
core_oaipmh_provider_app/components/oai_data/api.py
core_oaipmh_provider_app/components/oai_data/models.py
core_oaipmh_provider_app/components/oai_data/watch.py
core_oaipmh_provider_app/components/oai_provider_metadata_format/__init__.py
core_oaipmh_provider_app/components/oai_provider_metadata_format/api.py
core_oaipmh_provider_app/components/oai_provider_metadata_format/discover.py
core_oaipmh_provider_app/components/oai_provider_metadata_format/models.py
core_oaipmh_provider_app/components/oai_provider_set/__init__.py
core_oaipmh_provider_app/components/oai_provider_set/api.py
core_oaipmh_provider_app/components/oai_provider_set/models.py
core_oaipmh_provider_app/components/oai_request_page/__init__.py
core_oaipmh_provider_app/components/oai_request_page/api.py
core_oaipmh_provider_app/components/oai_request_page/models.py
core_oaipmh_provider_app/components/oai_settings/__init__.py
core_oaipmh_provider_app/components/oai_settings/api.py
core_oaipmh_provider_app/components/oai_settings/discover.py
core_oaipmh_provider_app/components/oai_settings/models.py
core_oaipmh_provider_app/components/oai_xsl_template/__init__.py
core_oaipmh_provider_app/components/oai_xsl_template/api.py
core_oaipmh_provider_app/components/oai_xsl_template/models.py
core_oaipmh_provider_app/migrations/0001_initial.py
core_oaipmh_provider_app/migrations/0002_oai_data_on_delete.py
