Metadata-Version: 2.1
Name: core-oaipmh-provider-app
Version: 2.19.0
Summary: OAI-PMH provider capabilities for the curator core project
Home-page: https://github.com/usnistgov/core_oaipmh_provider_app
Author: NIST IT Lab
Author-email: itl_inquiries@nist.gov
License-File: LICENSE.md
